setup.py
rhine/__init__.py
rhine/datatypes.py
rhine/exceptions.py
rhine/functions.py
rhine/instances.py
rhine.egg-info/PKG-INFO
rhine.egg-info/SOURCES.txt
rhine.egg-info/dependency_links.txt
rhine.egg-info/requires.txt
rhine.egg-info/top_level.txt