Metadata-Version: 1.1
Name: rhine
Version: 1.0.1
Summary: Rhine Python Client
Home-page: https://github.com/Speare/rhine-python
Author: Speare Inc.
Author-email: admin@rhine.io
License: New BSD
Platform: UNKNOWN
Classifier: Intended Audience :: Developers
Classifier: Natural Language :: English
Classifier: License :: OSI Approved :: BSD License
Classifier: Operating System :: OS Independent
Classifier: Programming Language :: Python
Classifier: Programming Language :: Python :: 2
Classifier: Programming Language :: Python :: 3
